print2message/__init__.py
print2message-1.1.0.dist-info/METADATA
print2message-1.1.0.dist-info/WHEEL
print2message-1.1.0.dist-info/top_level.txt
print2message-1.1.0.dist-info/RECORD
