Metadata-Version: 2.1
Name: print2message
Version: 1.1.0
Summary: Forward 'print' content
Home-page: https://github.com/LogicJake/print2message
Author: LogicJake
Author-email: chenyangshi1996@gamil.com
License: MIT
Platform: UNKNOWN
Requires-Dist: requests
Requires-Dist: PyYAML
